LWT/__init__.py
LWT/lmtanalysis/A-OldAnimal-.py
LWT/lmtanalysis/Animal-.py
LWT/lmtanalysis/Animal.py
LWT/lmtanalysis/BehaviouralSequencesUtil.py
LWT/lmtanalysis/BuildDataBaseIndex.py
LWT/lmtanalysis/BuildEventApproachContact.py
LWT/lmtanalysis/BuildEventApproachRear.py
LWT/lmtanalysis/BuildEventCenterPeripheryLocation.py
LWT/lmtanalysis/BuildEventDetection.py
LWT/lmtanalysis/BuildEventDistance.py
LWT/lmtanalysis/BuildEventExclusiveCleanOralOralSideSideNoseAnogenitalContact.py
LWT/lmtanalysis/BuildEventExclusiveMoveStopIsolated.py
LWT/lmtanalysis/BuildEventExclusiveUndetected.py
LWT/lmtanalysis/BuildEventFloorSniffing.py
LWT/lmtanalysis/BuildEventFollowZone.py
LWT/lmtanalysis/BuildEventGetAway.py
LWT/lmtanalysis/BuildEventGroup2.py
LWT/lmtanalysis/BuildEventGroup3.py
LWT/lmtanalysis/BuildEventGroup3MakeBreak.py
LWT/lmtanalysis/BuildEventGroup4.py
LWT/lmtanalysis/BuildEventGroup4MakeBreak.py
LWT/lmtanalysis/BuildEventHuddling.py
LWT/lmtanalysis/BuildEventMove.py
LWT/lmtanalysis/BuildEventNest3.py
LWT/lmtanalysis/BuildEventNest4.py
LWT/lmtanalysis/BuildEventNight.py
LWT/lmtanalysis/BuildEventObjectSniffingNor.py
LWT/lmtanalysis/BuildEventObjectSniffingNorAcquisitionWithConfig.py
LWT/lmtanalysis/BuildEventObjectSniffingNorTestWithConfig.py
LWT/lmtanalysis/BuildEventOnHouse.py
LWT/lmtanalysis/BuildEventOralGenitalContact.py
LWT/lmtanalysis/BuildEventOralOralContact.py
LWT/lmtanalysis/BuildEventOralSideSequence.py
LWT/lmtanalysis/BuildEventOtherContact.py
LWT/lmtanalysis/BuildEventPassiveAnogenitalSniff.py
LWT/lmtanalysis/BuildEventRear5.py
LWT/lmtanalysis/BuildEventRearCenterPeriphery.py
LWT/lmtanalysis/BuildEventSAP.py
LWT/lmtanalysis/BuildEventSideBySide.py
LWT/lmtanalysis/BuildEventSideBySideOpposite.py
LWT/lmtanalysis/BuildEventSideWalk.py
LWT/lmtanalysis/BuildEventSocialApproach.py
LWT/lmtanalysis/BuildEventSocialEscape.py
LWT/lmtanalysis/BuildEventStop.py
LWT/lmtanalysis/BuildEventTrain2.py
LWT/lmtanalysis/BuildEventTrain3.py
LWT/lmtanalysis/BuildEventTrain4.py
LWTools-1.1.4.dist-info/LICENSE
LWTools-1.1.4.dist-info/METADATA
LWTools-1.1.4.dist-info/WHEEL
LWTools-1.1.4.dist-info/top_level.txt
LWTools-1.1.4.dist-info/RECORD
