Metadata-Version: 2.1
Name: LWTools
Version: 1.1.4
Summary: Tool for LMT data analysis
Home-page: https://github.com/PaulCarrascosa/LMT_Widget_Tool-LWT
Author: Paul Carrascosa, Damien Huzard
Author-email: paul.carrascosa@igf.cnrs.fr
License: GNU General Public License v3 (GPLv3)
Keywords: Live Mouse Tracker,LMT,Tool,Data analysis
Classifier: Programming Language :: Python :: 3.10
Classifier: License :: OSI Approved :: GNU General Public License v3 (GPLv3)
Classifier: Operating System :: OS Independent
Requires-Python: >=3.10
License-File: LICENSE
Requires-Dist: setuptools >=61.0
Requires-Dist: tqdm ==4.65.0
Requires-Dist: matplotlib ==3.5.2
Requires-Dist: lxml ==4.9.1
Requires-Dist: pandas ==1.5.0
Requires-Dist: affine ==2.3.1
Requires-Dist: networkx ==2.8.5
Requires-Dist: seaborn ==0.11.2
Requires-Dist: dabest ==2023.2.14
Requires-Dist: statsmodels ==0.13.2
Requires-Dist: tabulate ==0.8.10
Requires-Dist: ipywidgets ==8.0.3
Requires-Dist: jupyterlab ==3.5.0
Requires-Dist: scipy ==1.9.3
Requires-Dist: numpy ==1.22.3
